bing_search_xiaomei/__init__.py
bing_search_xiaomei/server.py
bing_search_xiaomei-1.1.1.dist-info/METADATA
bing_search_xiaomei-1.1.1.dist-info/WHEEL
bing_search_xiaomei-1.1.1.dist-info/entry_points.txt
bing_search_xiaomei-1.1.1.dist-info/RECORD
