Metadata-Version: 2.4
Name: bing-search-xiaomei
Version: 1.1.1
Summary: a bing search tool for mt users
Author-email: yangming43 <yangming43@meituan.com>
Requires-Python: >=3.10
Requires-Dist: mcp>=1.1.2
Requires-Dist: requests==2.32.3
